d3m/hc/__init__.py
d3m/hc/collection.py
d3m/hc/command_handler.py
d3m/hc/conditions.py
d3m/hc/py.typed
d3m/hc/subscribe_config.py
dddmisc_handlers_collection-0.6.0.dist-info/LICENSE
dddmisc_handlers_collection-0.6.0.dist-info/METADATA
dddmisc_handlers_collection-0.6.0.dist-info/WHEEL
dddmisc_handlers_collection-0.6.0.dist-info/RECORD
