Metadata-Version: 2.1
Name: dddmisc-handlers-collection
Version: 0.6.0
Summary: This package provides implementation a collection of command’s and event’s handlers
Home-page: https://dddmisc.github.io/dddmisc-docs/
License: MIT
Author: Vladislav Vorobyov
Author-email: vladislav.vorobyov@gmail.com
Requires-Python: >=3.10,<4.0
Classifier: License :: OSI Approved :: MIT License
Classifier: Programming Language :: Python :: 3
Classifier: Programming Language :: Python :: 3.10
Classifier: Programming Language :: Python :: 3.11
Classifier: Programming Language :: Python :: 3.12
Requires-Dist: dddmisc-core (>=0.7.0,<0.8.0)
Requires-Dist: tenacity (>=8.0.0,<9.0.0)
Project-URL: Repository, https://github.com/dddmisc/dddmisc
